Topsis_Jashan_102017034
